networking_infoblox/__init__.py
networking_infoblox/_i18n.py
networking_infoblox/ipam/__init__.py
networking_infoblox/ipam/driver.py
networking_infoblox/ipam/requests.py
networking_infoblox/neutron/__init__.py
networking_infoblox/neutron/cmd/__init__.py
networking_infoblox/neutron/cmd/eventlet/__init__.py
networking_infoblox/neutron/cmd/eventlet/infoblox_ipam_agent.py
networking_infoblox/neutron/common/__init__.py
networking_infoblox/neutron/common/config.py
networking_infoblox/neutron/common/constants.py
networking_infoblox/neutron/common/context.py
networking_infoblox/neutron/common/dns.py
networking_infoblox/neutron/common/ea_manager.py
networking_infoblox/neutron/common/exceptions.py
networking_infoblox/neutron/common/grid.py
networking_infoblox/neutron/common/ip_allocator.py
networking_infoblox/neutron/common/ipam.py
networking_infoblox/neutron/common/keystone_manager.py
networking_infoblox/neutron/common/mapping.py
networking_infoblox/neutron/common/member.py
networking_infoblox/neutron/common/notification.py
networking_infoblox/neutron/common/notification_handler.py
networking_infoblox/neutron/common/pattern.py
networking_infoblox/neutron/common/utils.py
networking_infoblox/neutron/db/__init__.py
networking_infoblox/neutron/db/infoblox_db.py
networking_infoblox/neutron/db/infoblox_models.py
networking_infoblox/neutron/db/migration/__init__.py
networking_infoblox/neutron/db/migration/alembic_migrations/README
networking_infoblox/neutron/db/migration/alembic_migrations/__init__.py
networking_infoblox/neutron/db/migration/alembic_migrations/env.py
networking_infoblox/neutron/db/migration/alembic_migrations/script.py.mako
networking_infoblox/neutron/db/migration/alembic_migrations/versions/0075c5a73439_network_name_change_support.py
networking_infoblox/neutron/db/migration/alembic_migrations/versions/172ace2194db_add_infoblox_ipam_driver.py
networking_infoblox/neutron/db/migration/alembic_migrations/versions/256b90dd9824_add_dns_view_column_to_network_views.py
networking_infoblox-19.0.0.dist-info/AUTHORS
networking_infoblox-19.0.0.dist-info/LICENSE
networking_infoblox-19.0.0.dist-info/METADATA
networking_infoblox-19.0.0.dist-info/WHEEL
networking_infoblox-19.0.0.dist-info/entry_points.txt
networking_infoblox-19.0.0.dist-info/pbr.json
networking_infoblox-19.0.0.dist-info/top_level.txt
networking_infoblox-19.0.0.dist-info/RECORD
