Metadata-Version: 2.1
Name: networking-infoblox
Version: 19.0.0
Summary: Contains Neutron drivers for integration with Infoblox grids for IPAM and DNS.
Home-page: https://launchpad.net/networking-infoblox/
Author: OpenStack
Author-email: openstack-dev@lists.openstack.org
License: UNKNOWN
Platform: UNKNOWN
Classifier: Environment :: OpenStack
Classifier: Intended Audience :: Information Technology
Classifier: Intended Audience :: System Administrators
Classifier: License :: OSI Approved :: Apache Software License
Classifier: Operating System :: POSIX :: Linux
Classifier: Programming Language :: Python
Classifier: Programming Language :: Python :: 2
Classifier: Programming Language :: Python :: 2.7
Classifier: Programming Language :: Python :: 3
Classifier: Programming Language :: Python :: 3.3
Classifier: Programming Language :: Python :: 3.4
Classifier: Programming Language :: Python :: 3.8
Requires-Dist: Babel (>=1.3)
Requires-Dist: infoblox-client (==0.4.21)
Requires-Dist: neutron (>=19.0.0)
Requires-Dist: oslo.log (>=4.6.0)
